pipify/__init__.py
pipify/__main__.py
pipify/cli.py
pipify/create_python_project.py
pipify/generator.py
pipify/py.typed
pipify/requirements-dev.txt
pipify/requirements.txt
pipify/template/.darglint
pipify/template/.gitignore
pipify/template/MANIFEST.in
pipify/template/README.md
pipify/template/pyproject.toml
pipify/template/setup.py
pipify/template/.github/workflows/publish.yml
pipify/template/.github/workflows/test.yml
pipify/template/project/__init__.py
pipify/template/project/py.typed
pipify/template/project/requirements-dev.txt
pipify/template/project/requirements.txt
pipify/template/tests/conftest.py
pipify/template/tests/test_dummy.py
pipify-0.0.20.dist-info/licenses/LICENSE
pipify-0.0.20.dist-info/METADATA
pipify-0.0.20.dist-info/WHEEL
pipify-0.0.20.dist-info/entry_points.txt
pipify-0.0.20.dist-info/top_level.txt
pipify-0.0.20.dist-info/RECORD
