Metadata-Version: 2.4
Name: pipify
Version: 0.0.20
Summary: Utility for making python packages
Home-page: https://github.com/kscalelabs/pipify
Author: alik-git
Requires-Python: >=3.11
License-File: LICENSE
Requires-Dist: GitPython
Provides-Extra: dev
Requires-Dist: black; extra == "dev"
Requires-Dist: darglint; extra == "dev"
Requires-Dist: mypy; extra == "dev"
Requires-Dist: pytest; extra == "dev"
Requires-Dist: ruff; extra == "dev"
Dynamic: author
Dynamic: description
Dynamic: description-content-type
Dynamic: home-page
Dynamic: license-file
Dynamic: provides-extra
Dynamic: requires-dist
Dynamic: requires-python
Dynamic: summary
